{
  "status": "SUCCESS",
  "threshold": 0.67,
  "total_splits": 8,
  "successful_splits": 8,
  "failed_splits": 0,
  "precision_mean": 0.5580071001676316,
  "precision_median": 0.6181706150746398,
  "precision_std": 0.36190724672399105,
  "precision_min": 0.0,
  "precision_max": 1.0,
  "signals_mean": 359.375,
  "signals_median": 176.5,
  "signals_min": 0,
  "signals_max": 969,
  "ev_mean": 31.598418387008312,
  "ev_median": 30.31916344290348,
  "ev_std": 40.83651241980989,
  "splits": [
    {
      "status": "SUCCESS",
      "train_period": "2025-03-01 \u2192 2025-05-31",
      "test_period": "2025-06-01 \u2192 2025-06-30",
      "test_month": "2025-06",
      "train_samples": 42230,
      "test_samples": 14730,
      "train_positives": 19390,
      "test_positives": 6327,
      "threshold": 0.67,
      "total_signals": 0,
      "true_positives": 0,
      "false_positives": 0,
      "false_negatives": 6327,
      "true_negatives": 8403,
      "precision": 0.0,
      "recall": 0.0,
      "signal_rate": 0.0,
      "tp_avg_gain_pct": 0.0,
      "fp_avg_loss_pct": 0.0,
      "expected_value_pct": 0.0,
      "split_index": 1
    },
    {
      "status": "SUCCESS",
      "train_period": "2025-04-01 \u2192 2025-06-30",
      "test_period": "2025-07-01 \u2192 2025-07-31",
      "test_month": "2025-07",
      "train_samples": 41252,
      "test_samples": 16557,
      "train_positives": 18291,
      "test_positives": 6704,
      "threshold": 0.67,
      "total_signals": 721,
      "true_positives": 384,
      "false_positives": 337,
      "false_negatives": 6320,
      "true_negatives": 9516,
      "precision": 0.5325936199722607,
      "recall": 0.057279236276849645,
      "signal_rate": 0.04354653620825029,
      "tp_avg_gain_pct": 48.249358365404134,
      "fp_avg_loss_pct": -34.88095248427293,
      "expected_value_pct": 9.39372070057588,
      "split_index": 2
    },
    {
      "status": "SUCCESS",
      "train_period": "2025-05-01 \u2192 2025-07-31",
      "test_period": "2025-08-01 \u2192 2025-08-31",
      "test_month": "2025-08",
      "train_samples": 45861,
      "test_samples": 15037,
      "train_positives": 19238,
      "test_positives": 6437,
      "threshold": 0.67,
      "total_signals": 11,
      "true_positives": 0,
      "false_positives": 11,
      "false_negatives": 6437,
      "true_negatives": 8589,
      "precision": 0.0,
      "recall": 0.0,
      "signal_rate": 0.000731528895391368,
      "tp_avg_gain_pct": 0.0,
      "fp_avg_loss_pct": -31.428396871945257,
      "expected_value_pct": -31.428396871945257,
      "split_index": 3
    },
    {
      "status": "SUCCESS",
      "train_period": "2025-06-01 \u2192 2025-08-31",
      "test_period": "2025-09-01 \u2192 2025-09-30",
      "test_month": "2025-09",
      "train_samples": 46324,
      "test_samples": 16293,
      "train_positives": 19468,
      "test_positives": 7175,
      "threshold": 0.67,
      "total_signals": 819,
      "true_positives": 557,
      "false_positives": 262,
      "false_negatives": 6618,
      "true_negatives": 8856,
      "precision": 0.6800976800976801,
      "recall": 0.07763066202090592,
      "signal_rate": 0.0502669858221322,
      "tp_avg_gain_pct": 68.66460766064887,
      "fp_avg_loss_pct": -36.17860948255893,
      "expected_value_pct": 35.12501927051402,
      "split_index": 4
    },
    {
      "status": "SUCCESS",
      "train_period": "2025-07-01 \u2192 2025-09-30",
      "test_period": "2025-10-01 \u2192 2025-10-31",
      "test_month": "2025-10",
      "train_samples": 47887,
      "test_samples": 17134,
      "train_positives": 20316,
      "test_positives": 7020,
      "threshold": 0.67,
      "total_signals": 328,
      "true_positives": 228,
      "false_positives": 100,
      "false_negatives": 6792,
      "true_negatives": 10014,
      "precision": 0.6951219512195121,
      "recall": 0.03247863247863248,
      "signal_rate": 0.019143223999066185,
      "tp_avg_gain_pct": 72.15020675249322,
      "fp_avg_loss_pct": -38.64094584391521,
      "expected_value_pct": 38.37241632675894,
      "split_index": 5
    },
    {
      "status": "SUCCESS",
      "train_period": "2025-08-01 \u2192 2025-10-31",
      "test_period": "2025-11-01 \u2192 2025-11-30",
      "test_month": "2025-11",
      "train_samples": 48464,
      "test_samples": 12813,
      "train_positives": 20632,
      "test_positives": 6114,
      "threshold": 0.67,
      "total_signals": 25,
      "true_positives": 25,
      "false_positives": 0,
      "false_negatives": 6089,
      "true_negatives": 6699,
      "precision": 1.0,
      "recall": 0.004088976120379457,
      "signal_rate": 0.0019511433700148287,
      "tp_avg_gain_pct": 114.74515319926944,
      "fp_avg_loss_pct": 0.0,
      "expected_value_pct": 114.74515319926944,
      "split_index": 6
    },
    {
      "status": "SUCCESS",
      "train_period": "2025-09-01 \u2192 2025-11-30",
      "test_period": "2025-12-01 \u2192 2025-12-31",
      "test_month": "2025-12",
      "train_samples": 46240,
      "test_samples": 15241,
      "train_positives": 20309,
      "test_positives": 6336,
      "threshold": 0.67,
      "total_signals": 969,
      "true_positives": 539,
      "false_positives": 430,
      "false_negatives": 5797,
      "true_negatives": 8475,
      "precision": 0.5562435500515995,
      "recall": 0.08506944444444445,
      "signal_rate": 0.06357850534741814,
      "tp_avg_gain_pct": 68.19349448530497,
      "fp_avg_loss_pct": -27.985810345024444,
      "expected_value_pct": 25.513307615292945,
      "split_index": 7
    },
    {
      "status": "SUCCESS",
      "train_period": "2025-10-01 \u2192 2025-12-31",
      "test_period": "2026-01-01 \u2192 2026-01-31",
      "test_month": "2026-01",
      "train_samples": 45188,
      "test_samples": 14016,
      "train_positives": 19470,
      "test_positives": 6321,
      "threshold": 0.67,
      "total_signals": 2,
      "true_positives": 2,
      "false_positives": 0,
      "false_negatives": 6319,
      "true_negatives": 7695,
      "precision": 1.0,
      "recall": 0.00031640563202024995,
      "signal_rate": 0.00014269406392694063,
      "tp_avg_gain_pct": 61.06612685560053,
      "fp_avg_loss_pct": 0.0,
      "expected_value_pct": 61.06612685560053,
      "split_index": 8
    }
  ]
}